Metadata-Version: 2.1
Name: threesplit
Version: 0.1.1
Summary: Three-way data split into training set, validation set, and test set.
Home-page: http://github.com/kmedian/threesplit
Author: Ulf Hamster
Author-email: 554c46@gmail.com
License: Apache License 2.0
Platform: UNKNOWN
Requires-Python: >=3.6
